{"version":"1.0.0","resources":{"rootPath":{"model":"http://model.3dmomoda.cn/","texture":"https://static.3dmomoda.com/textures/"},"models":[{"title":"马路牙","size":[1,0.2,0.2],"version":"7","url":"9DD39737B6D14BD4B369D124F052C0CB","id":1},{"title":"圈地（无框）","size":[1,0.01,0.06],"version":"2","url":"5a250ed1b93b455e81b8c659fe528a89","id":2},{"title":"围墙样式03","size":[4.516,1.836,0.265],"version":"7","url":"D8F91C97318F4534844104C4BAACF03E","id":3},{"title":"绿化带2","size":[1.2,0.646,0.65],"version":"1","url":"0003826aea654a14a6f393a0aa0db91a","id":4},{"title":"园区围墙","size":[3.8,2.044,0.324],"version":"9","url":"41974EEFC2D14D02BB5E330286171C78","id":5},{"title":"铁艺大门","size":[3.7,2.3,0.1],"version":"6","url":"37948D3F65784617A91F6832B2273FF7","id":6},{"title":"叉车_动画","size":[1.399,2.292,3.439],"version":"2","hasAnimation":true,"url":"fea1e799ff4c4ec595fde2f76df12e15","id":7},{"title":"乔树02","size":[7.3,7.4,6.1],"version":"3","url":"d5b06cf7-2a31-4252-8d7c-02d48815ed18","id":8},{"title":"整车","size":[1.794,1.632,3.462],"version":"2","url":"a4d6aa769ae44cf19731734562c7561c","id":9},{"title":"棚子","size":[3.127,3.897,3.127],"version":"2","url":"c27192c2bd034e00b8249ff9755ca0f8","id":10},{"title":"地面","size":[56.729,0.001,49.55],"version":"1","url":"9eeffb69c42640dea913765c7ca88efd","id":11},{"title":"旗帜_新","size":[4.465,11.617,4.465],"version":"1","url":"0b66a8a801b04bd5a1a28d3bbfa721fe","id":12},{"title":"新厂房","size":[62.795,7.837,29.921],"version":"1","url":"96be9349311645bf9c25a37352453ed4","id":13},{"title":"室内玻璃隔断墙","size":[1.5,3,0.081],"version":"21","url":"C9FB3F9A29C842F79F02CECC4037FEA1","id":14},{"title":"门2.3*2.4","size":[2.3,2.4,0.1],"version":"6","url":"5E9D1E80510049329DDB708A56E36224","id":15},{"title":"双开玻璃门","size":[1.628,3,0.1],"version":"6","url":"83A4A1A772C44D3E8E9A676D5619C311","id":16},{"title":"双开窗户","size":[1.2,1.5,0.1],"version":"4","url":"76ED51063B2A4165ACB15AAF0190EB95","id":17},{"title":"会议桌_02","size":[3.275,0.679,1.003],"version":"2","url":"5fdf9e15a7d24ea08bae8385881b9d1a","id":18},{"title":"办公椅_02","size":[0.636,0.945,0.679],"version":"2","url":"16c82f412dd54ca1aaff00c5ea36addc","id":19},{"title":"笔记本电脑","size":[0.408,0.285,0.336],"version":"1","url":"1a7c54828ce34de8b7114aebcd0977c5","id":20},{"title":"饮水机","size":[0.261,1.065,0.265],"version":"2","url":"313bae0187a84d68865400db7ff93865","id":21},{"title":"水桶","size":[0.224,0.405,0.224],"version":"1","url":"e782b21befdf4730a863d15f1a445d1a","id":22},{"title":"椅子F","size":[0.498,0.773,0.502],"version":"6","url":"CC3A708A00CD4398A080C2E3AEC7E85D","id":23},{"title":"简约白色桌子","size":[0.001,0.001,0.001],"version":"5","url":"6F1C3EEB59E54910BE44EFA56667E2C1","id":24},{"title":null,"size":[0.9,1.77,0.47],"version":"1","hasAnimation":true,"url":"d881d40678504960803c1356c0d7a407","id":25},{"title":"门1.5*2.4","size":[1.5,2.4,0.1],"version":"6","url":"47298A825C224BE5882D01A9E8D7FED3","id":26},{"title":"停车位","size":[2.5,0.001,5],"version":"6","url":"3E99382A030A4640A7B83A709035EBD8","id":27}],"textures":[{"ext":"jpg","url":"vciip8gtjtuqt4q68hm0oifov9h0ox87","id":1},{"ext":"jpg","url":"3ED6C5B945CC420EBB6BE2C0F4CC84A5","id":2},{"url":"81FDB96B43D441C5B3C650BFA2B76CD4","title":"白墙","ext":"jpg","isDefault":true,"id":3},{"url":"EB9ECFA1101C4A0ABB770ED3A9865441","ext":"jpg","id":4},{"ext":"jpg","url":"IQR8PZE2SGEV2H07WX3EJK22CA6ZS0YG","id":5},{"ext":"jpg","url":"UPEUIZIK19VMBPP9TLZJ3J3ILWK8V5ZB","id":6},{"ext":"jpg","url":"3OZVGE55PV0MY48FPRG5BELXKHV26NU5","id":7}],"uuids":["4672","4671","4452","4225","4293","3445","1605","1606","2002","2003","2004","2005","2006","2007","2008","2009","2010","2011","2012","2013","2014","2271","2433","3776","3777","3778","3779","3780","3781","5290","6555","107","108","202","208","4107","4121","4126","589","Room","6243","6244","6245","6246","6248","6249","6250","6251","6252","Room2","Room3","121","353","381","380","379","425","432","450","478","382","516","542","541","540","543","544","545","546","547","6923","6924","6973","6967","2434","2278","2277","2276","2275","2274","2273","2272","2270"],"styles":[]},"objects":[{"uuid":6,"type":"Thing","name":"car01","position":[21.352,0.01,8.716],"userData":{"power":"40","Price":"JsonData array","Authority":"JsonData array","kuan":"JsonData array","chang":"JsonData array","gao":"JsonData array"},"body":{"id":7}},{"uuid":7,"type":"Thing","name":"car02","position":[24.101,0.01,8.896],"userData":{"power":"60","Price":"JsonData array","Authority":"JsonData array","kuan":"JsonData array","chang":"JsonData array","gao":"JsonData array"},"body":{"id":7}},{"uuid":8,"type":"Thing","position":[11.312,0.01,19.118],"scale":[0.55,0.55,0.55],"body":{"id":8}},{"uuid":9,"type":"Thing","position":[1.958,0.01,19.118],"quaternion":[0,0.45265046,0,0.89168804],"scale":[0.54,0.54,0.54],"body":{"id":8}},{"uuid":10,"type":"Thing","position":[-7.396,0.01,19.118],"quaternion":[0,-0.88577287,0,-0.46411898],"scale":[0.68,0.68,0.68],"body":{"id":8}},{"uuid":11,"type":"Thing","position":[-16.749,0.01,19.118],"quaternion":[0,-0.64392634,0,0.76508749],"scale":[0.52,0.52,0.52],"body":{"id":8}},{"uuid":12,"type":"Thing","position":[-26.103,0.01,19.118],"scale":[0.64,0.64,0.64],"body":{"id":8}},{"uuid":13,"type":"Thing","position":[-32.889,0.01,15.991],"quaternion":[0,-0.69836449,0,0.7157423],"scale":[0.64,0.64,0.64],"body":{"id":8}},{"uuid":14,"type":"Thing","position":[-32.889,0.01,9.678],"quaternion":[0,-0.88649263,0,0.46274271],"scale":[0.64,0.756,0.64],"body":{"id":8}},{"uuid":15,"type":"Thing","position":[-32.889,0.01,3.366],"quaternion":[0,-0.56488282,0,0.82517114],"scale":[0.64,0.64,0.64],"body":{"id":8}},{"uuid":16,"type":"Thing","position":[-32.889,0.01,-2.947],"quaternion":[0,-0.91034906,0,0.41384126],"scale":[0.563,0.563,0.563],"body":{"id":8}},{"uuid":17,"type":"Thing","position":[-21.257,0.01,19.688],"quaternion":[0,-0.69836449,0,0.7157423],"scale":[0.64,0.64,0.64],"body":{"id":8}},{"uuid":18,"type":"Thing","position":[-12.643,0.01,18.881],"quaternion":[0,-0.90648397,0,-0.42224023],"scale":[0.64,0.64,0.64],"body":{"id":8}},{"uuid":19,"type":"Thing","position":[-2.698,0.01,19.405],"quaternion":[0,-0.69836449,0,0.7157423],"scale":[0.64,0.493,0.64],"body":{"id":8}},{"uuid":20,"type":"Thing","position":[7.046,0.01,19.216],"quaternion":[0,0.04099346,0,0.99915941],"scale":[0.64,0.839,0.64],"body":{"id":8}},{"uuid":21,"type":"Thing","name":"car03","position":[8.369,0.01,14.5],"body":{"id":9}},{"uuid":22,"type":"Thing","position":[20.023,0.01,19.625],"body":{"id":10}},{"uuid":23,"type":"Thing","position":[32.25,0.01,15.989],"quaternion":[0,-0.69836449,0,0.7157423],"scale":[0.563,0.563,0.563],"body":{"id":8}},{"uuid":24,"type":"Thing","position":[32.25,0.01,11.793],"quaternion":[0,-0.84901619,0,0.52836683],"scale":[0.563,0.563,0.563],"body":{"id":8}},{"uuid":25,"type":"Thing","position":[32.25,0.01,7.598],"quaternion":[0,0.26600806,0,0.9639708],"scale":[0.575,0.608,0.608],"body":{"id":8}},{"uuid":26,"type":"Thing","position":[32.25,0.01,3.402],"quaternion":[0,-0.86603811,0,0.499978],"scale":[0.563,0.563,0.563],"body":{"id":8}},{"uuid":27,"type":"Thing","position":[32.25,0.01,-0.793],"quaternion":[0,-0.69836449,0,0.7157423],"scale":[0.563,0.563,0.563],"body":{"id":8}},{"uuid":28,"type":"Thing","position":[32.25,0.01,-4.988],"quaternion":[0,-0.87738315,0,0.47979039],"scale":[0.563,0.632,0.563],"body":{"id":8}},{"uuid":29,"type":"Thing","position":[0.117,0.01,0.071],"body":{"id":11}},{"uuid":30,"type":"Thing","name":"flag","position":[-16.389,0.01,5.781],"body":{"id":12}},{"uuid":31,"type":"Building","position":[0.782,0,-14.9],"tags":["主建筑"],"body":{"children":[{"position":[-1.021,0.1,-2.742],"quaternion":[0,-1,0,0],"id":13}]},"children":[{"uuid":32,"type":"Floor","name":"新楼层","position":[0,0,0],"children":[{"type":"Wall","external":{"walls":[{"thickness":0.15,"height":3,"points":[0,1],"lefttexture":3,"righttexture":3,"edgetexture":4},{"thickness":0.15,"height":3,"points":[2,3],"lefttexture":3,"righttexture":3,"edgetexture":4},{"thickness":0.15,"height":3,"points":[3,0],"lefttexture":3,"righttexture":3,"edgetexture":4},{"thickness":0.15,"height":3,"points":[1,4],"holes":[{"loc":[0.404,0],"size":[2.3,2.4,0.15]},{"loc":[0.6570000000000001,0],"size":[2.3,2.4,0.15]},{"loc":[0.8680000000000003,0.4],"size":[1.2,1.5,0.15]}],"lefttexture":3,"righttexture":3,"edgetexture":4},{"thickness":0.15,"height":3,"points":[4,5],"lefttexture":3,"righttexture":3,"edgetexture":4},{"thickness":0.15,"height":3,"points":[6,2],"lefttexture":3,"righttexture":3,"edgetexture":4},{"thickness":0.15,"height":3,"points":[5,7],"lefttexture":3,"righttexture":3,"edgetexture":4},{"thickness":0.15,"height":3,"points":[7,6],"lefttexture":3,"righttexture":3,"edgetexture":4}]}},{"type":"Wall","external":{"walls":[{"thickness":0.1,"height":3,"points":[8,4],"holes":[{"loc":[0.6959999999999998,0],"size":[1.628,3,0.1]}],"model":14},{"thickness":0.1,"height":3,"points":[9,8],"holes":[{"loc":[0.716,0],"size":[1.628,3,0.1]}],"model":14},{"thickness":0.1,"height":3,"points":[3,9],"model":14},{"thickness":0.1,"height":3,"points":[6,9],"holes":[{"loc":[0.574,0],"size":[1.628,3,0.1]}],"model":14},{"thickness":0.1,"height":3,"points":[7,8],"model":14}]}},{"uuid":33,"type":"Door","name":"door","position":[7.385807999999997,0,10.295],"quaternion":[0,0,0,1],"scale":[1,1,1.4999999999999998],"userData":{},"body":{"id":15}},{"uuid":34,"type":"Door","name":"door","position":[-5.579936000000007,0,10.295],"quaternion":[0,0,0,1],"scale":[1,1,1.4999999999999998],"userData":{},"body":{"id":15}},{"uuid":35,"type":"Door","name":"door","position":[-23.158,0,7.569335999999998],"quaternion":[0,0.7071067811865476,0,-0.7071067811865475],"scale":[1,1,1],"userData":{},"body":{"id":16}},{"uuid":36,"type":"Door","name":"door","position":[-23.158,0,-1.5731960000000003],"quaternion":[0,0.7071067811865476,0,-0.7071067811865475],"scale":[1,1,1],"userData":{},"body":{"id":16}},{"uuid":37,"type":"Door","name":"door","position":[-26.320624000000002,0,-8.89],"quaternion":[0,1,0,6.123233995736766e-17],"scale":[1,1,1],"userData":{},"body":{"id":16}},{"uuid":38,"type":"Window","name":"window","position":[-16.39326400000002,1.2000000000000002,10.295],"quaternion":[0,0,0,1],"scale":[1,1,1.4999999999999998],"userData":{},"body":{"id":17}},{"uuid":39,"type":"Room","name":"Room1","position":[-13.435000000000002,0,-1.8902500000000002],"userData":{},"external":{"corners":[8,7,6,9]},"children":[{"type":"Slab","external":{"height":0.01}},{"type":"Ceiling","visible":false,"external":{"height":2.999}},{"type":"Roof","visible":false,"external":{"height":3.001}},{"uuid":40,"type":"Thing","name":"cabinetB0","position":[-15.236999999999998,0.01,0.02725000000000022],"quaternion":[0,-0.69836447,0,0.71574232],"userData":{"Price":"JsonData array","Authority":"JsonData array","kuan":"JsonData array","chang":"JsonData array","gao":"JsonData array"},"body":{"id":18}},{"uuid":41,"type":"Thing","name":"cabinetB1","position":[-15.236999999999998,0.01,-3.24775],"quaternion":[0,-0.69836447,0,0.71574232],"userData":{"Price":"JsonData array","Authority":"JsonData array","kuan":"JsonData array","chang":"JsonData array","gao":"JsonData array"},"body":{"id":18}},{"uuid":42,"type":"Thing","name":"cabinetB2","position":[-16.171999999999997,0.01,0.19125000000000014],"quaternion":[0,0.69836447,0,0.71574232],"userData":{"Price":"JsonData array","Authority":"JsonData array","kuan":"JsonData array","chang":"JsonData array","gao":"JsonData array"},"body":{"id":19}},{"uuid":43,"type":"Thing","name":"cabinetB3","position":[-15.409999999999997,0.68,0.13525000000000031],"quaternion":[0,-0.69836447,0,0.71574232],"body":{"id":20}},{"uuid":44,"type":"Thing","position":[-10.506999999999998,0.01,-6.697749999999999],"body":{"id":21}},{"uuid":45,"type":"Thing","position":[-10.128999999999998,0.01,-6.5177499999999995],"body":{"id":22}},{"uuid":46,"type":"Thing","position":[-11.264,0.01,-6.210750000000001],"body":{"id":23}},{"uuid":47,"type":"Thing","position":[-11.245999999999999,0.01,-5.36375],"body":{"id":24}},{"uuid":48,"type":"Thing","name":"cabinetB4","position":[-15.394999999999996,0.01,-6.67075],"body":{"id":25}}]},{"uuid":49,"type":"Room","name":"Room2","position":[-13.435000000000002,0,2.9059999999999997],"userData":{},"external":{"corners":[7,8,4,5]},"children":[{"type":"Slab","external":{"height":0.01}},{"type":"Ceiling","visible":false,"external":{"height":2.999}},{"type":"Roof","visible":false,"external":{"height":3.001}}]},{"uuid":50,"type":"Room","name":"Room3","position":[-13.435000000000002,0,-6.111000000000001],"userData":{},"external":{"corners":[9,6,2,3]},"children":[{"type":"Slab","external":{"height":0.01}},{"type":"Ceiling","visible":false,"external":{"height":2.999}},{"type":"Roof","visible":false,"external":{"height":3.001}}]},{"uuid":51,"type":"Room","name":"room","position":[-3.037666666666667,0,-1.5065833333333334],"userData":{},"external":{"corners":[9,3,0,1,4,8]},"children":[{"type":"Slab","external":{"height":0.100000001490116,"texture":5}},{"type":"Ceiling","external":{"height":2.899,"texture":6}},{"type":"Roof","visible":false,"external":{"height":3.001,"texture":7}}]}],"external":{"corners":[[28.09,0,-15.554],[28.09,0,10.295],[-30.582000000000004,0,-15.554],[-23.158,0,-15.554],[-23.158,0,10.295],[-30.582000000000004,0,10.295],[-30.582000000000004,0,-8.89],[-30.582000000000004,0,1.329],[-23.158,0,1.329],[-23.158,0,-8.89]],"childrenUUID":[33,34,35,36,37,38,40,41,42,43,44,45,46,47,48]}},{"uuid":52,"type":"Floor","name":"新楼层","position":[0,3,0],"children":[{"type":"Wall","external":{"walls":[{"thickness":0.15,"height":3,"points":[0,1],"lefttexture":3,"righttexture":3,"edgetexture":4},{"thickness":0.15,"height":3,"points":[2,3],"lefttexture":3,"righttexture":3,"edgetexture":4},{"thickness":0.15,"height":3,"points":[3,0],"lefttexture":3,"righttexture":3,"edgetexture":4},{"thickness":0.15,"height":3,"points":[1,4],"holes":[{"loc":[0.867,0.4],"size":[1.2,1.5,0.15]},{"loc":[0.6700000000000002,0.4],"size":[1.2,1.5,0.15]},{"loc":[0.418,0.4],"size":[1.2,1.5,0.15]},{"loc":[0.16100000000000003,0.4],"size":[1.2,1.5,0.15]}],"lefttexture":3,"righttexture":3,"edgetexture":4},{"thickness":0.15,"height":3,"points":[4,5],"lefttexture":3,"righttexture":3,"edgetexture":4},{"thickness":0.15,"height":3,"points":[6,7],"lefttexture":3,"righttexture":3,"edgetexture":4},{"thickness":0.15,"height":3,"points":[6,2],"lefttexture":3,"righttexture":3,"edgetexture":4},{"thickness":0.15,"height":3,"points":[3,7],"holes":[{"loc":[0.598,0],"size":[1.5,2.4,0.15]}],"lefttexture":3,"righttexture":3,"edgetexture":4},{"thickness":0.15,"height":3,"points":[8,9],"lefttexture":3,"righttexture":3,"edgetexture":4},{"thickness":0.15,"height":3,"points":[5,8],"lefttexture":3,"righttexture":3,"edgetexture":4},{"thickness":0.15,"height":3,"points":[8,6],"lefttexture":3,"righttexture":3,"edgetexture":4},{"thickness":0.15,"height":3,"points":[7,9],"holes":[{"loc":[0.528,0],"size":[1.5,2.4,0.15]}],"lefttexture":3,"righttexture":3,"edgetexture":4},{"thickness":0.15,"height":3,"points":[9,4],"holes":[{"loc":[0.45499999999999996,0],"size":[1.5,2.4,0.15]}],"lefttexture":3,"righttexture":3,"edgetexture":4}]}},{"uuid":53,"type":"Door","name":"door","position":[-23.158,0,-11.568928],"quaternion":[0,0.7071067811865476,0,-0.7071067811865475],"scale":[1,1,1.4999999999999998],"userData":{},"body":{"id":26}},{"uuid":54,"type":"Door","name":"door","position":[-23.158,0,-3.4943679999999997],"quaternion":[0,0.7071067811865476,0,-0.7071067811865475],"scale":[1,1,1.4999999999999998],"userData":{},"body":{"id":26}},{"uuid":55,"type":"Door","name":"door","position":[-23.158,0,5.408529999999999],"quaternion":[0,0.7071067811865476,0,-0.7071067811865475],"scale":[1,1,1.4999999999999998],"userData":{},"body":{"id":26}},{"uuid":56,"type":"Window","name":"window","position":[-16.342016000000005,1.2000000000000002,10.295],"quaternion":[0,0,0,1],"scale":[1,1,1.4999999999999998],"userData":{},"body":{"id":17}},{"uuid":57,"type":"Window","name":"window","position":[-6.246160000000014,1.2000000000000002,10.295],"quaternion":[0,0,0,1],"scale":[1,1,1.4999999999999998],"userData":{},"body":{"id":17}},{"uuid":58,"type":"Window","name":"window","position":[6.668336,1.2000000000000002,10.295],"quaternion":[0,0,0,1],"scale":[1,1,1.4999999999999998],"userData":{},"body":{"id":17}},{"uuid":59,"type":"Window","name":"window","position":[19.839071999999998,1.2000000000000002,10.295],"quaternion":[0,0,0,1],"scale":[1,1,1.4999999999999998],"userData":{},"body":{"id":17}},{"uuid":60,"type":"Room","name":"room","position":[-3.0376666666666665,0,-1.5065833333333334],"userData":{},"external":{"corners":[4,9,7,3,0,1]},"children":[{"type":"Slab","external":{"height":0.01,"texture":5}},{"type":"Ceiling","external":{"height":2.899,"texture":6}},{"type":"Roof","visible":false,"external":{"height":3.001,"texture":7}}]},{"uuid":39,"type":"Room","name":"Room2","position":[-13.435000000000002,0,2.906],"userData":{},"external":{"corners":[9,4,5,8]},"children":[{"type":"Slab","external":{"height":0.01}},{"type":"Ceiling","visible":false,"external":{"height":2.999}},{"type":"Roof","visible":false,"external":{"height":3.001}}]},{"uuid":49,"type":"Room","name":"Room3","position":[-13.435000000000002,0,-1.8902500000000002],"userData":{},"external":{"corners":[7,9,8,6]},"children":[{"type":"Slab","external":{"height":0.01}},{"type":"Ceiling","visible":false,"external":{"height":2.999}},{"type":"Roof","visible":false,"external":{"height":3.001}}]},{"uuid":50,"type":"Room","name":"Room4","position":[-13.435000000000002,0,-6.111000000000001],"userData":{},"external":{"corners":[3,7,6,2]},"children":[{"type":"Slab","external":{"height":0.01}},{"type":"Ceiling","visible":false,"external":{"height":2.999}},{"type":"Roof","visible":false,"external":{"height":3.001}}]}],"external":{"corners":[[28.09,0,-15.554],[28.09,0,10.295],[-30.582000000000004,0,-15.554],[-23.158,0,-15.554],[-23.158,0,10.295],[-30.582000000000004,0,10.295],[-30.582000000000004,0,-8.89],[-23.158,0,-8.89],[-30.582000000000004,0,1.329],[-23.158,0,1.329]],"childrenUUID":[53,54,55,56,57,58,59]}},{"uuid":61,"type":"Floor","name":"新楼层","position":[0,6,0],"children":[{"type":"Wall","external":{"walls":[{"thickness":0.15,"height":3,"points":[0,1],"lefttexture":3,"righttexture":3,"edgetexture":4},{"thickness":0.15,"height":3,"points":[2,3],"lefttexture":3,"righttexture":3,"edgetexture":4},{"thickness":0.15,"height":3,"points":[3,0],"lefttexture":3,"righttexture":3,"edgetexture":4},{"thickness":0.15,"height":3,"points":[1,4],"holes":[{"loc":[0.867,0.4],"size":[1.2,1.5,0.15]},{"loc":[0.6700000000000003,0.4],"size":[1.2,1.5,0.15]},{"loc":[0.418,0.4],"size":[1.2,1.5,0.15]},{"loc":[0.16100000000000003,0.4],"size":[1.2,1.5,0.15]}],"lefttexture":3,"righttexture":3,"edgetexture":4},{"thickness":0.15,"height":3,"points":[4,5],"lefttexture":3,"righttexture":3,"edgetexture":4},{"thickness":0.15,"height":3,"points":[6,7],"lefttexture":3,"righttexture":3,"edgetexture":4},{"thickness":0.15,"height":3,"points":[6,2],"lefttexture":3,"righttexture":3,"edgetexture":4},{"thickness":0.15,"height":3,"points":[3,7],"holes":[{"loc":[0.598,0],"size":[1.5,2.4,0.15]}],"lefttexture":3,"righttexture":3,"edgetexture":4},{"thickness":0.15,"height":3,"points":[8,9],"lefttexture":3,"righttexture":3,"edgetexture":4},{"thickness":0.15,"height":3,"points":[5,8],"lefttexture":3,"righttexture":3,"edgetexture":4},{"thickness":0.15,"height":3,"points":[8,6],"lefttexture":3,"righttexture":3,"edgetexture":4},{"thickness":0.15,"height":3,"points":[7,9],"holes":[{"loc":[0.528,0],"size":[1.5,2.4,0.15]}],"lefttexture":3,"righttexture":3,"edgetexture":4},{"thickness":0.15,"height":3,"points":[9,4],"holes":[{"loc":[0.45499999999999985,0],"size":[1.5,2.4,0.15]}],"lefttexture":3,"righttexture":3,"edgetexture":4}]}},{"uuid":62,"type":"Door","name":"door","position":[-23.158,0,-11.568928],"quaternion":[0,0.7071067811865476,0,-0.7071067811865475],"scale":[1,1,1.4999999999999998],"userData":{},"body":{"id":26}},{"uuid":63,"type":"Door","name":"door","position":[-23.158,0,-3.4943679999999997],"quaternion":[0,0.7071067811865476,0,-0.7071067811865475],"scale":[1,1,1.4999999999999998],"userData":{},"body":{"id":26}},{"uuid":64,"type":"Door","name":"door","position":[-23.158,0,5.408529999999998],"quaternion":[0,0.7071067811865476,0,-0.7071067811865475],"scale":[1,1,1.4999999999999998],"userData":{},"body":{"id":26}},{"uuid":65,"type":"Window","name":"window","position":[-16.342016000000005,1.2000000000000002,10.295],"quaternion":[0,0,0,1],"scale":[1,1,1.4999999999999998],"userData":{},"body":{"id":17}},{"uuid":66,"type":"Window","name":"window","position":[-6.246160000000014,1.2000000000000002,10.295],"quaternion":[0,0,0,1],"scale":[1,1,1.4999999999999998],"userData":{},"body":{"id":17}},{"uuid":67,"type":"Window","name":"window","position":[6.668336,1.2000000000000002,10.295],"quaternion":[0,0,0,1],"scale":[1,1,1.4999999999999998],"userData":{},"body":{"id":17}},{"uuid":68,"type":"Window","name":"window","position":[19.839071999999998,1.2000000000000002,10.295],"quaternion":[0,0,0,1],"scale":[1,1,1.4999999999999998],"userData":{},"body":{"id":17}},{"uuid":69,"type":"Room","name":"room","position":[-3.0376666666666665,0,-1.5065833333333334],"userData":{},"external":{"corners":[4,9,7,3,0,1]},"children":[{"type":"Slab","external":{"height":0.01,"texture":5}},{"type":"Ceiling","external":{"height":2.899,"texture":6}},{"type":"Roof","visible":false,"external":{"height":3.001,"texture":7}}]},{"uuid":39,"type":"Room","name":"Room2","position":[-13.435000000000002,0,2.906],"userData":{},"external":{"corners":[9,4,5,8]},"children":[{"type":"Slab","external":{"height":0.01}},{"type":"Ceiling","visible":false,"external":{"height":2.999}},{"type":"Roof","visible":false,"external":{"height":3.001}}]},{"uuid":49,"type":"Room","name":"Room3","position":[-13.435000000000002,0,-1.8902500000000002],"userData":{},"external":{"corners":[7,9,8,6]},"children":[{"type":"Slab","external":{"height":0.01}},{"type":"Ceiling","visible":false,"external":{"height":2.999}},{"type":"Roof","visible":false,"external":{"height":3.001}}]},{"uuid":50,"type":"Room","name":"Room4","position":[-13.435000000000002,0,-6.111000000000001],"userData":{},"external":{"corners":[3,7,6,2]},"children":[{"type":"Slab","external":{"height":0.01}},{"type":"Ceiling","visible":false,"external":{"height":2.999}},{"type":"Roof","visible":false,"external":{"height":3.001}}]}],"external":{"corners":[[28.09,0,-15.554],[28.09,0,10.295],[-30.582000000000004,0,-15.554],[-23.158,0,-15.554],[-23.158,0,10.295],[-30.582000000000004,0,10.295],[-30.582000000000004,0,-8.89],[-23.158,0,-8.89],[-30.582000000000004,0,1.329],[-23.158,0,1.329]],"childrenUUID":[62,63,64,65,66,67,68]}}]},{"uuid":70,"type":"Building","position":[-24.379,0,8.844],"tags":["主建筑"],"children":[{"uuid":71,"type":"Floor","name":"新楼层","position":[0,0,0],"children":[{"type":"Wall","external":{"walls":[{"thickness":0.15,"height":3,"points":[0,1],"lefttexture":3,"righttexture":3,"edgetexture":4},{"thickness":0.15,"height":3,"points":[1,2],"holes":[{"loc":[0.18700000000000006,0],"size":[2.3,2.4,0.15]}],"lefttexture":3,"righttexture":3,"edgetexture":4},{"thickness":0.15,"height":3,"points":[2,3],"lefttexture":3,"righttexture":3,"edgetexture":4},{"thickness":0.15,"height":3,"points":[3,0],"lefttexture":3,"righttexture":3,"edgetexture":4}]}},{"uuid":72,"type":"Door","name":"door","position":[4.295,0,4.90415],"quaternion":[0,0.7071067811865475,0,0.7071067811865476],"scale":[1,1,1.4999999999999998],"userData":{},"body":{"id":15}},{"uuid":73,"type":"Room","name":"room","position":[-0.4282499999999998,0,0.01849999999999974],"userData":{},"external":{"corners":[0,3,2,1]},"children":[{"type":"Slab","external":{"height":0.0500000007450581,"texture":5}},{"type":"Ceiling","external":{"height":2.899,"texture":6}},{"type":"Roof","external":{"height":3.001,"texture":7}}]}],"external":{"corners":[[-6.007999999999999,0,7.812],[4.295,0,7.812],[4.295,0,-7.738],[-6.007999999999999,0,-7.738]],"childrenUUID":[72]}}]},{"uuid":74,"type":"Group","position":[0.129,0.039,14.226],"children":[{"uuid":75,"type":"Thing","position":[11.375,0,0],"quaternion":[0,-1,0,0],"body":{"id":27}},{"uuid":76,"type":"Thing","position":[8.125,0,0],"quaternion":[0,-1,0,0],"body":{"id":27}},{"uuid":77,"type":"Thing","position":[4.875,0,0],"quaternion":[0,-1,0,0],"body":{"id":27}},{"uuid":78,"type":"Thing","position":[1.625,0,0],"quaternion":[0,-1,0,0],"body":{"id":27}},{"uuid":79,"type":"Thing","position":[-1.625,0,0],"quaternion":[0,-1,0,0],"body":{"id":27}},{"uuid":80,"type":"Thing","position":[-4.875,0,0],"quaternion":[0,-1,0,0],"body":{"id":27}},{"uuid":81,"type":"Thing","position":[-8.125,0,0],"quaternion":[0,-1,0,0],"body":{"id":27}},{"uuid":82,"type":"Thing","position":[-11.376,0,0],"quaternion":[0,-1,0,0],"body":{"id":27}}]},{"type":"Ground","external":{"corners":[[-12.249,0,-3.05],[-12.249,0,-0.847],[-12.771,0,0.138],[-14.223,0,0.604],[-30.716,0,0.604],[-31.416,0,-2.13],[-31.416,0,-3.176],[-31.335,0,-27.916],[-31.34,0,-32.714],[31.214,0,-32.714],[31.214,0,20.528],[29.87,0,21.097],[27.837,0,21.435],[18.587,0,21.435],[18.587,0,19.485],[18.587,0,18.357],[18.123,0,17.357],[17.122,0,16.89],[16.092,0,16.89],[-30.716,0,16.89],[-24.565,0,21.435],[-27.538,0,20.808],[-29.549,0,20.284],[-31.502,0,19.526],[-33.135,0,18.476],[-34.155,0,16.89],[-34.709,0,15.824],[-35.234,0,13.958],[-35.622,0,11.451],[-35.622,0,-28.115],[-35.622,0,-28.724],[-35.1,0,-31.484],[-33.966,0,-33.891],[-32.42,0,-35.671],[-30.213,0,-37.211],[-27.248,0,-38.241],[-24.558,0,-38.704],[-21.486,0,-39.222],[20.757,0,-39.222],[23.84,0,-38.495],[26.435,0,-37.578],[29.022,0,-35.88],[31.214,0,-34.229],[32.637,0,-31.768],[33.345,0,-30.167],[33.853,0,-28.115],[33.853,0,13.526],[33.543,0,15.748],[33.139,0,18.02],[32.497,0,19.44],[-20.452,0,2.076],[-20.452,0,10.437]]},"children":[{"uuid":0,"type":"Slab","external":{"texture":1,"corners":[0,1,2,3,4,5,6]}},{"uuid":1,"type":"Slab","external":{"texture":2,"corners":[1,0,6,7,8,9,10,11,12,13,14,15,16,17,18,19,4,3,2]}},{"uuid":2,"type":"Slab","external":{"texture":1,"corners":[5,4,19,18,17,16,15,14,13,20,21,22,23,24,25,26,27,28,29,8,7,6]}},{"uuid":3,"type":"Slab","external":{"texture":1,"corners":[9,8,29,30,31,32,33,34,35,36,37,38,39,40,41,42,43,44,45]}},{"uuid":4,"type":"Slab","external":{"texture":1,"corners":[10,9,45,46,47,48,49]}},{"type":"Wall","external":{"walls":[{"points":[29,30],"height":0.2,"thickness":0.1,"model":1},{"points":[8,29],"height":0.2,"thickness":0.1,"model":1},{"points":[50,51],"height":0.2,"thickness":0.1,"model":1},{"points":[5,4],"height":0.2,"thickness":0.1,"model":1},{"points":[4,19],"height":0.2,"thickness":0.1,"model":1},{"points":[0,6],"height":0.01,"thickness":0.1,"model":2},{"points":[6,5],"height":0.01,"thickness":0.1,"model":2},{"points":[45,9],"height":0.2,"thickness":0.1,"model":1},{"points":[9,8],"height":0.2,"thickness":0.1,"model":1},{"points":[38,39],"height":1.836,"thickness":0.1,"model":3},{"points":[39,40],"height":1.836,"thickness":0.1,"model":3},{"points":[40,41],"height":1.836,"thickness":0.1,"model":3},{"points":[41,42],"height":1.836,"thickness":0.1,"model":3},{"points":[42,43],"height":1.836,"thickness":0.1,"model":3},{"points":[43,44],"height":1.836,"thickness":0.1,"model":3},{"points":[44,45],"height":1.836,"thickness":0.1,"model":3},{"points":[30,31],"height":1.836,"thickness":0.1,"model":3},{"points":[31,32],"height":1.836,"thickness":0.1,"model":3},{"points":[32,33],"height":1.836,"thickness":0.1,"model":3},{"points":[33,34],"height":1.836,"thickness":0.1,"model":3},{"points":[34,35],"height":1.836,"thickness":0.1,"model":3},{"points":[35,36],"height":1.836,"thickness":0.1,"model":3},{"points":[36,37],"height":1.836,"thickness":0.1,"model":3},{"points":[37,38],"height":1.836,"thickness":0.1,"model":3},{"points":[28,27],"height":1.836,"thickness":0.1,"model":3},{"points":[28,29],"height":1.836,"thickness":0.1,"model":3},{"points":[27,26],"height":1.836,"thickness":0.1,"model":3},{"points":[26,25],"height":1.836,"thickness":0.1,"model":3},{"points":[25,24],"height":1.836,"thickness":0.1,"model":3},{"points":[24,23],"height":1.836,"thickness":0.1,"model":3},{"points":[23,22],"height":1.836,"thickness":0.1,"model":3},{"points":[22,21],"height":1.836,"thickness":0.1,"model":3},{"points":[21,20],"height":1.836,"thickness":0.1,"model":3},{"points":[13,20],"height":1.836,"thickness":0.1,"model":3},{"points":[12,11],"height":1.836,"thickness":0.1,"model":3},{"points":[12,13],"height":1.836,"thickness":0.1,"model":3,"holes":[{"loc":[0.40789189189189184,0],"size":[4.9987,0.1,3.9997]}]},{"points":[11,10],"height":1.836,"thickness":0.1,"model":3},{"points":[10,49],"height":1.836,"thickness":0.1,"model":3},{"points":[9,10],"height":0.2,"thickness":0.1,"model":1},{"points":[49,48],"height":1.836,"thickness":0.1,"model":3},{"points":[48,47],"height":1.836,"thickness":0.1,"model":3},{"points":[47,46],"height":1.836,"thickness":0.1,"model":3},{"points":[45,46],"height":1.836,"thickness":0.1,"model":3},{"points":[19,18],"height":0.2,"thickness":0.1,"model":1},{"points":[14,13],"height":0.2,"thickness":0.1,"model":1},{"points":[16,15],"height":0.2,"thickness":0.1,"model":1},{"points":[15,14],"height":0.2,"thickness":0.1,"model":1},{"points":[18,17],"height":0.2,"thickness":0.1,"model":1},{"points":[17,16],"height":0.2,"thickness":0.1,"model":1},{"points":[2,3],"height":0.646,"thickness":0.1,"model":4},{"points":[3,4],"height":0.646,"thickness":0.1,"model":4},{"points":[0,1],"height":0.646,"thickness":0.1,"model":4},{"points":[1,2],"height":0.646,"thickness":0.1,"model":4},{"points":[8,7],"height":2.044,"thickness":0.1,"model":5},{"points":[7,6],"height":0.01,"thickness":0.1,"model":2}]}},{"uuid":5,"type":"Door","position":[24.064,0,21.435],"scale":[1.351,1.739,1],"body":{"id":6}}]}],"external":{"childrenUUID":[6,7,8,9,10,11,12,13,14,15,16,17,18,19,20,21,22,23,24,25,26,27,28,29,30,75,76,77,78,79,80,81,82]}}